glesys/__init__.py
glesys/exceptions.py
glesys/glesys.py
glesys/mixins.py
glesys/endpoints/__init__.py
glesys/endpoints/base.py
glesys/endpoints/server.py
glesys/endpoints/user.py
pyglesys-0.1.0.dev0.dist-info/LICENSE
pyglesys-0.1.0.dev0.dist-info/METADATA
pyglesys-0.1.0.dev0.dist-info/WHEEL
pyglesys-0.1.0.dev0.dist-info/top_level.txt
pyglesys-0.1.0.dev0.dist-info/RECORD
