Metadata-Version: 2.1
Name: pyglesys
Version: 0.1.0.dev0
Summary: Python wrapper around the GleSYS API
Home-page: https://github.com/pyglesys/pyglesys
Author: Erik Jansson Agnvall
Author-email: erikjansson90@gmail.com
License: MIT
Platform: UNKNOWN
Classifier: Development Status :: 4 - Beta
Classifier: Intended Audience :: Developers
Classifier: License :: OSI Approved :: MIT License
Classifier: Programming Language :: Python
Classifier: Programming Language :: Python :: 2
Classifier: Programming Language :: Python :: 2.7
Classifier: Programming Language :: Python :: 3
Classifier: Programming Language :: Python :: 3.4
Classifier: Programming Language :: Python :: 3.5
Classifier: Programming Language :: Python :: 3.6
Classifier: Programming Language :: Python :: 3.7
Requires-Python: >=2.7, !=3.0.*, !=3.1.*, !=3.2.*, !=3.3.*
Requires-Dist: requests (~=2.20)
Requires-Dist: Click (~=7.0)
